{
  "collectionName": "components_casestudy_section5s",
  "info": {
    "displayName": "section5",
    "icon": "th-list",
    "description": ""
  },
  "options": {},
  "attributes": {
    "heading": {
      "type": "string"
    },
    "headingColor": {
      "type": "string"
    },
    "bgImage": {
      "type": "media",
      "multiple": false,
      "required": false,
      "allowedTypes": [
        "images"
      ]
    },
    "centerImage": {
      "type": "media",
      "multiple": false,
      "required": false,
      "allowedTypes": [
        "images"
      ]
    },
    "leftImage": {
      "type": "media",
      "multiple": false,
      "required": false,
      "allowedTypes": [
        "images"
      ]
    },
    "rightImage": {
      "type": "media",
      "multiple": false,
      "required": false,
      "allowedTypes": [
        "images"
      ]
    },
    "text": {
      "type": "component",
      "repeatable": true,
      "component": "extras.multi-line-renderer"
    },
    "backgroundColor": {
      "type": "string"
    },
    "marginTop": {
      "type": "string"
    }
  }
}
